noventa/cli.py
noventa/noventa_bin/libpython3.10.so
noventa/noventa_bin/noventa
noventa/starter/cookiecutter.json
noventa/starter/hooks/post_gen_project.py
noventa/starter/{{cookiecutter.project_name}}/.gitignore
noventa/starter/{{cookiecutter.project_name}}/AGENTS.md
noventa/starter/{{cookiecutter.project_name}}/CLAUDE.md
noventa/starter/{{cookiecutter.project_name}}/GEMINI.md
noventa/starter/{{cookiecutter.project_name}}/__init__.py
noventa/starter/{{cookiecutter.project_name}}/config.yaml
noventa/starter/{{cookiecutter.project_name}}/requirements.txt
noventa/starter/{{cookiecutter.project_name}}/components/__init__.py
noventa/starter/{{cookiecutter.project_name}}/files/.gitkeep
noventa/starter/{{cookiecutter.project_name}}/functions/.gitkeep
noventa/starter/{{cookiecutter.project_name}}/functions/__init__.py
noventa/starter/{{cookiecutter.project_name}}/layouts/.gitkeep
noventa/starter/{{cookiecutter.project_name}}/migrations/__init__.py
noventa/starter/{{cookiecutter.project_name}}/migrations/alembic.ini
noventa/starter/{{cookiecutter.project_name}}/migrations/env.py
noventa/starter/{{cookiecutter.project_name}}/migrations/script.py.mako
noventa/starter/{{cookiecutter.project_name}}/migrations/seed/.gitkeep
noventa/starter/{{cookiecutter.project_name}}/migrations/seed/__init__.py
noventa/starter/{{cookiecutter.project_name}}/migrations/versions/__init__.py
noventa/starter/{{cookiecutter.project_name}}/models/__init__.py
noventa/starter/{{cookiecutter.project_name}}/pages/.gitkeep
noventa-0.1.0a4.dist-info/METADATA
noventa-0.1.0a4.dist-info/WHEEL
noventa-0.1.0a4.dist-info/entry_points.txt
noventa-0.1.0a4.dist-info/top_level.txt
noventa-0.1.0a4.dist-info/RECORD
