Metadata-Version: 2.4
Name: noventa
Version: 0.1.0a4
Author: Marcos Macedo
License: Apache-2.0
Project-URL: Homepage, https://noventa.dev
Requires-Python: ~=3.10
Requires-Dist: cookiecutter==2.6.0
Requires-Dist: SQLAlchemy==2.0.44
Requires-Dist: alembic==1.17.0
Requires-Dist: werkzeug==3.1.3
